countonlyonechar/__init__.py
countonlyonechar/collect_framework.py
countonlyonechar/main.py
countonlyonechar-1.0.0.dist-info/licenses/LICENSE
tests/__init__.py
tests/test_collect_framework.py
tests/test_main.py
countonlyonechar-1.0.0.dist-info/METADATA
countonlyonechar-1.0.0.dist-info/WHEEL
countonlyonechar-1.0.0.dist-info/entry_points.txt
countonlyonechar-1.0.0.dist-info/top_level.txt
countonlyonechar-1.0.0.dist-info/RECORD
